borkpipeline/__init__.py
borkpipeline/pipeline.py
tests/__init__.py
tests/test_pipeline.py
borkpipeline-1.0.0.dist-info/LICENSE
borkpipeline-1.0.0.dist-info/METADATA
borkpipeline-1.0.0.dist-info/WHEEL
borkpipeline-1.0.0.dist-info/top_level.txt
borkpipeline-1.0.0.dist-info/RECORD
