Metadata-Version: 2.1
Name: borkpipeline
Version: 1.0.0
Summary: A library that implements the Chain of Responsibility pattern.
Author: Matthew Batchelder
Author-email: Matthew Batchelder <borkweb@gmail.com>
License: MIT License
Project-URL: Homepage, https://github.com/borkweb/borkpipeline
Keywords: pipeline,library
Classifier: License :: OSI Approved :: MIT License
Classifier: Programming Language :: Python
Classifier: Programming Language :: Python :: 3
Requires-Python: >=3.8
License-File: LICENSE
